<annotation>
	<folder>Damage</folder>
	<filename>1352.jpeg</filename>
	<path>/Volumes/T5/mit stuff/Mini-project/6th sem project/Dataset/annotations/annotated/Damage/1352.jpeg</path>
	<source>
		<database>Unknown</database>
	</source>
	<size>
		<width>259</width>
		<height>194</height>
		<depth>3</depth>
	</size>
	<segmented>0</segmented>
	<object>
		<name>Broken-glass</name>
		<pose>Unspecified</pose>
		<truncated>0</truncated>
		<difficult>0</difficult>
		<bndbox>
			<xmin>126</xmin>
			<ymin>99</ymin>
			<xmax>165</xmax>
			<ymax>129</ymax>
		</bndbox>
	</object>
	<object>
		<name>Dent</name>
		<pose>Unspecified</pose>
		<truncated>0</truncated>
		<difficult>0</difficult>
		<bndbox>
			<xmin>187</xmin>
			<ymin>86</ymin>
			<xmax>211</xmax>
			<ymax>104</ymax>
		</bndbox>
	</object>
	<object>
		<name>Smashed</name>
		<pose>Unspecified</pose>
		<truncated>0</truncated>
		<difficult>0</difficult>
		<bndbox>
			<xmin>133</xmin>
			<ymin>89</ymin>
			<xmax>232</xmax>
			<ymax>181</ymax>
		</bndbox>
	</object>
</annotation>
